CarvePie
