Metadata-Version: 1.0
Name: CarvePie
Version: 0.2
Summary: Python helper for python ninja
Home-page: http://github.com/saqirzzq/CarvePy
Author: Saqib Razzaq
Author-email: saqi.cb@gmail.com
License: MIT
Platform: UNKNOWN
